filex/__init__.py
filex/cli.py
teserak_filex-0.0.1.dist-info/METADATA
teserak_filex-0.0.1.dist-info/WHEEL
teserak_filex-0.0.1.dist-info/entry_points.txt
teserak_filex-0.0.1.dist-info/RECORD
