Metadata-Version: 2.4
Name: teserak-filex
Version: 0.0.1
Summary: Add your description here
Requires-Python: >=3.13
Requires-Dist: typer>=0.19.2
